geoflight_replay/__init__.py
geoflight_replay/capture.py
geoflight_replay/cli.py
geoflight_replay/constants.py
geoflight_replay/interactive_cli.py
geoflight_replay/object_spawner.py
geoflight_replay/simconnect_utils.py
geoflight_replay/windows_utils.py
geoflight_replay-1.0.0.dist-info/LICENSE.txt
geoflight_replay-1.0.0.dist-info/METADATA
geoflight_replay-1.0.0.dist-info/WHEEL
geoflight_replay-1.0.0.dist-info/entry_points.txt
geoflight_replay-1.0.0.dist-info/top_level.txt
geoflight_replay-1.0.0.dist-info/RECORD
