Metadata-Version: 2.2
Name: geoflight_replay
Version: 1.0.0
Summary: Replay and capture scenarios of positions in Flight Simulator 2020
Author: Jean-Brice Ginestet, Vincent Mussot
Author-email: vincent.mussot@irt-saintexupery.com
Classifier: Programming Language :: Python :: 3
Classifier: License :: OSI Approved :: MIT License
Classifier: Operating System :: Microsoft :: Windows
Requires-Python: >=3.6
License-File: LICENSE.txt
Requires-Dist: click>=8.1.0
Requires-Dist: colorama>=0.4.0
Requires-Dist: comtypes>=1.2.0
Requires-Dist: dxcam>=0.0.5
Requires-Dist: keyboard>=0.13.0
Requires-Dist: lunr>=0.7.0
Requires-Dist: numpy>=1.26.0
Requires-Dist: opencv-python>=4.8.1
Requires-Dist: PyGetWindow>=0.0.9
Requires-Dist: PyRect>=0.2.0
Requires-Dist: PyYAML>=6.0.1
Requires-Dist: SimConnect>=0.4.26
Requires-Dist: typer>=0.9.0
Requires-Dist: pyautogui>=0.9.54
Requires-Dist: typing_extensions>=4.8.0
Dynamic: author
Dynamic: author-email
Dynamic: classifier
Dynamic: requires-dist
Dynamic: requires-python
Dynamic: summary
